clims/__init__.py
clims/construct_wigner_seitz_cluster.py
clims/elements.py
clims/phonopy_interface.py
clims/plot_mulliken.py
clims/prepare_input.py
clims/prepare_submission.py
clims/read_band_data.py
clims/read_control.py
clims/read_dos_data.py
clims/structure.py
clims/testsuite_tools.py
clims/cli/__init__.py
clims/cli/aimsplot.py
clims/cli/citations.py
clims/cli/configure.py
clims/cli/convert.py
clims/cli/elastic_constants.py
clims/cli/mace.py
clims/cli/phonons.py
clims/cli/prepare_run.py
clims/cli/reinitialize_geometry.py
clims/cli/supercell.py
clims/cli/testsuite.py
clims/cli/unit_cell_info.py
clims/cli/wigner_seitz_cluster.py
clims/cli/xyplot.py
test/__init__.py
test/file_comparison.py
test/test_convert_coordinates.py
test/test_elastic_constants.py
test/test_mace.py
test/test_phonons.py
test/test_prepare_run.py
test/test_supercell.py
test/test_unit_cell_info.py
test/test_wigner_seitz_cluster.py
clims-0.7.3.dist-info/LICENSE
clims-0.7.3.dist-info/METADATA
clims-0.7.3.dist-info/WHEEL
clims-0.7.3.dist-info/entry_points.txt
clims-0.7.3.dist-info/top_level.txt
clims-0.7.3.dist-info/RECORD
