Metadata-Version: 2.1
Name: clims
Version: 0.7.3
Summary: Command-Line Interface for Materials Simulations
Home-page: https://gitlab.com/FHI-aims-club/utilities/clims
Author: FHI-aims developers
License: LGPLv2.1+
Classifier: License :: OSI Approved :: GNU Lesser General Public License v2 or later (LGPLv2+)
Classifier: Programming Language :: Python :: 3
Classifier: Programming Language :: Python :: 3.9
Requires-Python: >=3.9
License-File: LICENSE
Requires-Dist: ase >=3.23
Requires-Dist: spglib >=2.5.0
Requires-Dist: phonopy >=2.9.3
Requires-Dist: matplotlib >=3.4.1
Requires-Dist: click >=7.1.2
Requires-Dist: pytest >=6.2.3
Requires-Dist: numpy <2.0
Requires-Dist: Elastic >=0.1
Provides-Extra: mace
Requires-Dist: mace-torch ==0.3.6 ; extra == 'mace'
